main.py
mdxlate/__init__.py
mdxlate/cache.py
mdxlate/cli.py
mdxlate/client.py
mdxlate/start_translation.py
mdxlate/translator.py
mdxlate-1.1.5.dist-info/METADATA
mdxlate-1.1.5.dist-info/WHEEL
mdxlate-1.1.5.dist-info/entry_points.txt
mdxlate-1.1.5.dist-info/top_level.txt
mdxlate-1.1.5.dist-info/RECORD
