Metadata-Version: 2.4
Name: mdxlate
Version: 1.1.5
Summary: Translate Markdown docs into multiple languages using LLMs with smart caching and custom prompts
Author-email: Softoft <tobias.bueck@softoft.de>
License: MIT
Project-URL: Homepage, https://softoft-orga.github.io/markdown-automatic-translation/
Project-URL: Documentation, https://softoft-orga.github.io/markdown-automatic-translation/
Project-URL: Repository, https://github.com/Softoft-Orga/markdown-automatic-translation
Project-URL: Issues, https://github.com/Softoft-Orga/markdown-automatic-translation/issues
Keywords: markdown,translation,i18n,localization,llm,openai,documentation,multilingual
Classifier: Development Status :: 4 - Beta
Classifier: Intended Audience :: Developers
Classifier: Topic :: Documentation
Classifier: Topic :: Software Development :: Localization
Classifier: Topic :: Text Processing :: Markup :: Markdown
Classifier: License :: OSI Approved :: MIT License
Classifier: Programming Language :: Python :: 3
Classifier: Programming Language :: Python :: 3.10
Classifier: Programming Language :: Python :: 3.11
Classifier: Programming Language :: Python :: 3.12
Requires-Python: >=3.10
Requires-Dist: typer>=0.19.2
Requires-Dist: openai>=2.3.0
Requires-Dist: tenacity>=8.2
Requires-Dist: pytest>=8.4.2
Requires-Dist: setuptools>=69
Requires-Dist: wheel>=0.45.1
